yomiel/__init__.py
yomiel/__main__.py
yomiel/app.py
yomiel/cache.py
yomiel/log.py
yomiel/data/__init__.py
yomiel/data/config/yomiel.yaml
yomiel/data/config/logger/__init__.py
yomiel/data/config/logger/yomiel.yaml
yomiel/subsys/__init__.py
yomiel/subsys/log.py
yomiel-1.1.0.dist-info/LICENSE
yomiel-1.1.0.dist-info/METADATA
yomiel-1.1.0.dist-info/NOTICE
yomiel-1.1.0.dist-info/WHEEL
yomiel-1.1.0.dist-info/entry_points.txt
yomiel-1.1.0.dist-info/top_level.txt
yomiel-1.1.0.dist-info/zip-safe
yomiel-1.1.0.dist-info/RECORD
