Metadata-Version: 2.1
Name: yomiel
Version: 1.1.0
Summary: Pretty printer for jomiel messages
Home-page: https://github.com/guendto/jomiel-yomiel
Author: Toni Gündoğdu
Author-email: 47444442+guendto@users.noreply.github.com
License: Apache2.0
Platform: any
Classifier: Development Status :: 4 - Beta
Classifier: License :: OSI Approved :: Apache Software License
Classifier: Programming Language :: Python :: 3.6
Classifier: Programming Language :: Python :: 3.7
Classifier: Programming Language :: Python :: 3.8
Classifier: Programming Language :: Python :: 3.9
Requires-Python: >=3.6
License-File: LICENSE
License-File: NOTICE
Requires-Dist: jomiel-comm
Requires-Dist: jomiel-kore (>=0.2.2)
